MANIFEST.in
Makefile
README.md
requirements.txt
setup.cfg
setup.py
bin/cldrive
cldrive/__init__.py
cldrive/args.py
cldrive/cgen.py
cldrive/data.py
cldrive/driver.py
cldrive/env.py
cldrive.egg-info/PKG-INFO
cldrive.egg-info/SOURCES.txt
cldrive.egg-info/dependency_links.txt
cldrive.egg-info/not-zip-safe
cldrive.egg-info/requires.txt
cldrive.egg-info/top_level.txt