Metadata-Version: 1.0
Name: cldrive
Version: 0.0.14
Summary: Run arbitrary OpenCL kernels
Home-page: https://github.com/ChrisCummins/cldrive
Author: Chris Cummins
Author-email: chrisc.101@gmail.com
License: GNU General Public License, Version 3
Platform: UNKNOWN
